spoceatmos/__init__.py
spoceatmos/util.py
spoceatmos-1.0.dist-info/METADATA
spoceatmos-1.0.dist-info/WHEEL
spoceatmos-1.0.dist-info/entry_points.txt
spoceatmos-1.0.dist-info/top_level.txt
spoceatmos-1.0.dist-info/RECORD
