Metadata-Version: 2.1
Name: spoceatmos
Version: 1.0
Summary: Space & Oceanic & Atmospheric Data Collector
Home-page: https://lno1.com/spoceatmos
Author: xiehai
Author-email: xiehai@vip.qq.com
License: MIT Licence
Keywords: Space,Oceanic,Atmospheric
Platform: any
